pipeline/__init__.py
pipeline/__main__.py
pipeline/cloud/__init__.py
pipeline/cloud/asyncio/__init__.py
pipeline/cloud/asyncio/pipelines.py
pipeline/cloud/compute_requirements.py
pipeline/cloud/files.py
pipeline/cloud/http.py
pipeline/cloud/logs.py
pipeline/cloud/pipelines.py
pipeline/cloud/pointers.py
pipeline/cloud/runs.py
pipeline/cloud/schemas/__init__.py
pipeline/cloud/schemas/cluster.py
pipeline/cloud/schemas/files.py
pipeline/cloud/schemas/pagination.py
pipeline/cloud/schemas/pipelines.py
pipeline/cloud/schemas/pointers.py
pipeline/cloud/schemas/registry.py
pipeline/cloud/schemas/runs.py
pipeline/configuration/__init__.py
pipeline/console/__init__.py
pipeline/console/cluster.py
pipeline/console/commands.py
pipeline/console/container/__init__.py
pipeline/console/container/build.py
pipeline/console/container/convert.py
pipeline/console/container/init_dir.py
pipeline/console/container/pointer.py
pipeline/console/container/push.py
pipeline/console/container/schemas.py
pipeline/console/container/up.py
pipeline/console/logs.py
pipeline/console/targets/__init__.py
pipeline/console/targets/files.py
pipeline/console/targets/pipelines.py
pipeline/console/targets/pointers.py
pipeline/console/targets/resources.py
pipeline/console/targets/scaling_configs.py
pipeline/container/__init__.py
pipeline/container/docker_templates/__init__.py
pipeline/container/docker_templates/cog_dockerfile_template.txt
pipeline/container/docker_templates/dockerfile_template.txt
pipeline/container/docker_templates/pipeline_template.py
pipeline/container/docker_templates/readme_template.md
pipeline/container/docker_templates/turbo_registry_template.txt
pipeline/container/frameworks/cog.py
pipeline/container/frontend/.babelrc
pipeline/container/frontend/README.md
pipeline/container/frontend/package-lock.json
pipeline/container/frontend/package.json
pipeline/container/frontend/postcss.config.js
pipeline/container/frontend/src/components/Header.tsx
pipeline_ai-2.8.0.dist-info/LICENSE
pipeline_ai-2.8.0.dist-info/METADATA
pipeline_ai-2.8.0.dist-info/WHEEL
pipeline_ai-2.8.0.dist-info/entry_points.txt
pipeline_ai-2.8.0.dist-info/RECORD
