Metadata-Version: 2.1
Name: pipeline-ai
Version: 2.8.0
Summary: Pipelines for machine learning workloads.
License: Apache-2.0
Author: Paul Hetherington
Author-email: ph@mystic.ai
Requires-Python: >=3.10,<4.0
Classifier: License :: OSI Approved :: Apache Software License
Classifier: Programming Language :: Python :: 3
Classifier: Programming Language :: Python :: 3.10
Classifier: Programming Language :: Python :: 3.11
Classifier: Programming Language :: Python :: 3.12
Requires-Dist: PyYAML (>=6.0,<7.0)
Requires-Dist: cloudpickle (>=2.2.0,<3.0.0)
Requires-Dist: docker (>=7.1.0,<8.0.0)
Requires-Dist: fastapi (>=0.105.0,<0.106.0)
Requires-Dist: httpx (>=0.27.0,<0.28.0)
Requires-Dist: pydantic (>=1.8.2,<2.0.0)
Requires-Dist: pyhumps (>=3.8.0,<4.0.0)
Requires-Dist: requests (>=2.32.3,<3.0.0)
Requires-Dist: requests-toolbelt (>=1.0.0,<2.0.0)
Requires-Dist: tabulate (>=0.9.0,<0.10.0)
Requires-Dist: tqdm (>=4.66.1,<5.0.0)
Requires-Dist: websockets (>=10.4)
